{
  "name": "Henrietta Horton",
  "age": 40,
  "address": {
    "street": "Kufud Avenue",
    "city": "Mufufegij",
    "state": "NC",
    "zip": "22011"
  },
  "contact": {
    "phone": "(828) 662-3743",
    "servicePhone": "800219357"
  },
  "birthday": "1975-07-29T08:58:38.131Z",
  "ip": "69.236.201.167",
  "foo": "bar",
  "profile": {
    "about": "Ur ocoow jajali wodir arza sudujion ganuv datse rej il fujoata jenes rohtubriz osguen fowca. Dit ci bojsugtuz bot ascowaw mofmuwow ful ihomozgo hucizi kurpivo weog daemgev cikih fiv ta rogviwnuj huwcan azwuov. Tihcivla elcuso hiag pe tezunew bu panmi ikajod uwgujuw ahaca sifdifra hutrel osu zumojoko ka sobvubzo fi ser. Okja ceolvav riesewiz bus tezbeeb dutozro abu vug je sejesoabu noetogo zak horfidu. Nes larva jipbespu henoh zecverif jazij ta ez folpefnu enkoga gal fietora wa fudnun voj inuelo wa.",
    "bio": "Tomopdul adfu lalimpi dofsifis si azufeccac jesirmuw ge kec worhiv jaah vulat rihe. Umigek humobok solides jod sefitu tev netra bonodu ehaduasi pibmahu adi wefop umaunuhil ova wut sasijnum. Wukbighuk holego ajolwi ru huwumha sovuhla judce fe kazuzo nam jo najfaiha kehlite nabme zutha diug dez safesa. Waklebi ev aw hosove puz ceguvuc ec katok umo ramjet wo rofeh es uc duc. Tikzimo bo hawvoli lakfa zar gi bihoz pujgafi dup waz mo rohzili zadsud save. Ihpe teig to surpam hiksu wihe tunidedur cut gaosigi umi idde mac zi tireduhur rion pu du oju."
  },
  "apiKey": "bb834be868f03eb66d6c60e089699a30bb6945fe54c73b255103f08a155d2309",
  "currency": {
    "code": "KGS",
    "name": "Kyrgyzstan Som"
  }
}