{
  "name": "Phillip McGee",
  "age": 44,
  "address": {
    "street": "Toteh Boulevard",
    "city": "Hoguvbo",
    "state": "NJ",
    "zip": "03701"
  },
  "contact": {
    "phone": "(778) 455-5515",
    "servicePhone": "800136121"
  },
  "birthday": "2002-09-10T10:00:46.925Z",
  "ip": "76.202.224.219",
  "foo": "bar",
  "profile": {
    "about": "Se ba limpe nosifacev widjog irkergo piuni evato nojraspes pohaw diiwuluc furir tace ud ogkageg. Fubedju foc jahbuhtu so piefiku komloam mu taca loit ja rarenhoz tebcunre ebiitoso. Pujhari zok feutigu wozbu nunil dosawuj hocum widzo rolra amocutoh egedo louh odusadcih ta wozimume adeluma hurifgog oj. Carom det muk hacum otgohbu wubnozno lawahcar woop citawiv ze nu pa ijmon cav.",
    "bio": "Tak la cemduduv na wag jitinu nilru eju zajnug rod aseteg wait mijogdu ubkewus si hukawos gekalsur. Ugesened wujcifa ni ciim refepubi meram jovgevip zolehohor weeki zucef kusibipe howbata agutaoja ti hawohi tohwag. Joronso zukze zigtam ji ajjajjow un uviez cupane ros jovto zanput mez rajlucnek og sufeul uzpob ore me."
  },
  "apiKey": "0159ed25eafa7e5e00cd123d53b6f9137e689e456463d6576a10abf4c1184e58",
  "currency": {
    "code": "MMK",
    "name": "Myanmar (Burma) Kyat"
  }
}