{
  "name": "Joseph Bowman",
  "age": 61,
  "address": {
    "street": "Mocka Trail",
    "city": "Canuhli",
    "state": "NE",
    "zip": "84005"
  },
  "contact": {
    "phone": "(863) 580-1574",
    "servicePhone": "800913222"
  },
  "birthday": "1996-05-15T10:11:12.350Z",
  "ip": "167.45.25.52",
  "foo": "bar",
  "profile": {
    "about": "Gir gif bavma rezoga gucuwir oruloz vok dicca elo gokra koviz ef. Vok rawavca gunaap mu bug bit om em me hejadu rimu ce kinvihdib ade sakagez palhuf. Gip kemi obnihnow deafu amoidu re et nucoku dur wep zadgohzib ipi go ba. Jihorgi bu are todwo dah la vuc gefeh uzmare mu baweh fowooc vic sena da tolruhe pave fukaza. Ricvovuj haira gal hizver jebos fo bawpi ziesa bithem mu cupuvaru norig ekuseco bulgozmef. Ramofpet gaculgu da wuthizpit mazgowtu fo bop aleketije huoje go ul wi risga uhci lakbafi. Dog lepubbuw dip navzegcoc deuk lu wecujcig sariv epi vuilkep nivsaus jupenlo hiiru voz pu mavkihvul fa.",
    "bio": "Ubo kesala uwi fuippe gefusus er cipwosoh godauw ge olo uj zaddi kupuvre usaop ovvot de zukig jifat. Zundimor edakabe ac nu cacu ige ovufukmiv zohikma ickoh kaga limad guuku. Hav rudofo jofaw usdinle ure cisji ga udovomil biw zufpipita nuflaih eh fuvood miksic ojtucaw loz. Ugo gimle ibabote wapli za uhdo tehe votoniob cujuwavi demneiwu majfa gegwacef liufpo gukkaza hoen ju ubofop."
  },
  "apiKey": "fc79f7cc4a1ae1fb652e6b412c619d72b7ecee18f87de39265ba82a6e7ee4fa7",
  "currency": {
    "code": "STD",
    "name": "São Tomé and Príncipe Dobra"
  }
}