{
  "name": "Amy Klein",
  "age": 33,
  "address": {
    "street": "Lufum Avenue",
    "city": "Dupwueho",
    "state": "MO",
    "zip": "30529"
  },
  "contact": {
    "phone": "(964) 650-1837",
    "servicePhone": "800835131"
  },
  "birthday": "1959-03-21T05:24:50.268Z",
  "ip": "250.205.195.223",
  "foo": "bar",
  "profile": {
    "about": "Mah tehgo ko dof obidec upcarhew perlondor cahufuwug semsaror wacogaiv betawguv ize calkep dakzadcu kupub. Mose cob nisos noji poeg uremare vifudipo fucubikak nacuf afa sun vij wolovji sibo numrepac pupcefor sejaz. Dazu wevego hiw oreep behiodi ofpi ajo urugap nat wo ic lesfuni gekecwo gepzeg. Fufla ec amedibi luhulsic li ojpu nogul nim revevu me jacja hazag hudigap kolun. Dansipre ginfomji mef cofeg gugbaho lo hetzarelo zokaki lohrew wijel ipdaf hunoab vigol huc tajsonfo meto hocra. Id sajgicwar dib fupnu tazjivror fifjouj voh fawzo uwbubuw jovlem hecer rocwuot isno dahod beos hifnah.",
    "bio": "Regpevup neileco fohespeb cak anhavuh maboep jakusko bas oc mut vov rizahaubo cica heon. Hovgoj doodto wanibtu jipsatehe sus omueca abulagemo eladogku fobce aleza satmesma eti gup vilnev losucro pamfubus wuj. Uzpabdas le samjol catonun peslu vetta lepganfik duolu dumapoec zaw nezewi wapuzok. Fudpol ekijoj abe satonub heba duhe zoposve uci alego juod ces du kokis orumje hanehaku."
  },
  "apiKey": "1a580f775f91de1e4bde778da1bcac637f9e1be3eac8208e6da14703cc2186e1",
  "currency": {
    "code": "LYD",
    "name": "Libya Dinar"
  }
}